homeassistant_bring_api/__init__.py
homeassistant_bring_api/bring.py
homeassistant_bring_api/exceptions.py
homeassistant_bring_api/types.py
homeassistant_bring_api-0.1.0.dist-info/LICENSE
homeassistant_bring_api-0.1.0.dist-info/METADATA
homeassistant_bring_api-0.1.0.dist-info/WHEEL
homeassistant_bring_api-0.1.0.dist-info/top_level.txt
homeassistant_bring_api-0.1.0.dist-info/RECORD
