Metadata-Version: 2.1
Name: homeassistant-bring-api
Version: 0.1.0
Summary: Unofficial home assistant python package to access Bring! shopping lists API.
Home-page: https://github.com/miaucl/python-bring-api
Author: Cyrill Raccaud
Author-email: cyrill.raccaud+pypi@gmail.com
Classifier: Programming Language :: Python :: 3
Classifier: License :: OSI Approved :: MIT License
Classifier: Operating System :: OS Independent
Requires-Python: >=3.8
License-File: LICENSE
Requires-Dist: aiohttp
